atlasbroker/__init__.py
atlasbroker/backend.py
atlasbroker/broker.py
atlasbroker/config.py
atlasbroker/errors.py
atlasbroker/service.py
atlasbroker/servicebinding.py
atlasbroker/serviceinstance.py
atlasbroker/storage.py
atlasbroker/apis/__init__.py
atlasbroker/apis/broker.py
atlasbroker/apis/health.py
atlasbroker-2.0.0.dist-info/METADATA
atlasbroker-2.0.0.dist-info/RECORD
atlasbroker-2.0.0.dist-info/WHEEL
atlasbroker-2.0.0.dist-info/top_level.txt
