Metadata-Version: 2.1
Name: atlasbroker
Version: 2.0.0
Summary: Kubernetes Broker for MongoDB Atlas Cloud provider
Home-page: https://github.com/mickybart/python-atlasbroker
Author: Yellow Pages Inc.
Author-email: cloud@yp.ca
License: Apache License 2.0
Keywords: atlas,mongo,mongodb,cloud,kubernetes,broker
Platform: UNKNOWN
Classifier: Development Status :: 4 - Beta
Classifier: Intended Audience :: Developers
Classifier: License :: OSI Approved :: Apache Software License
Classifier: Operating System :: OS Independent
Classifier: Programming Language :: Python :: 3 :: Only
Classifier: Programming Language :: Python :: 3.5
Classifier: Programming Language :: Python :: 3.6
Classifier: Programming Language :: Python :: 3.7
Requires-Python: >=3.5
Requires-Dist: flask
Requires-Dist: openbrokerapi (>=2.0.0)
Requires-Dist: pymongo
Requires-Dist: pwgen
Requires-Dist: atlasapi
